docopt_parser/__init__.py
docopt_parser/__main__.py
docopt_parser/base/__init__.py
docopt_parser/base/group.py
docopt_parser/base/leaf.py
docopt_parser/base/node.py
docopt_parser/groups.py
docopt_parser/leaves/__init__.py
docopt_parser/leaves/argument.py
docopt_parser/leaves/argumentseparator.py
docopt_parser/leaves/command.py
docopt_parser/leaves/option.py
docopt_parser/leaves/options_shortcut.py
docopt_parser/options.py
docopt_parser/py.typed
docopt_parser/usage.py
docopt_parser/util/__init__.py
docopt_parser/util/errors.py
docopt_parser/util/helpers.py
docopt_parser/util/marks.py
docopt_parser/util/parsers.py
docopt_parser/util/post_processors.py
docopt_parser-0.0.1.dist-info/METADATA
docopt_parser-0.0.1.dist-info/WHEEL
docopt_parser-0.0.1.dist-info/entry_points.txt
docopt_parser-0.0.1.dist-info/RECORD
